README.md
setup.py
alibabacloud_darabonba_string/__init__.py
alibabacloud_darabonba_string/client.py
alibabacloud_darabonba_string_py2.egg-info/PKG-INFO
alibabacloud_darabonba_string_py2.egg-info/SOURCES.txt
alibabacloud_darabonba_string_py2.egg-info/dependency_links.txt
alibabacloud_darabonba_string_py2.egg-info/top_level.txt